specpink/__init__.py
specpink/example.py
specpink/pipeline.py
specpink/reducer.py
specpink/spectrum.py
specpink/stacker.py
specpink/utils.py
specpink-0.1.0.dist-info/licenses/LICENSE
specpink-0.1.0.dist-info/METADATA
specpink-0.1.0.dist-info/WHEEL
specpink-0.1.0.dist-info/top_level.txt
specpink-0.1.0.dist-info/RECORD
