Metadata-Version: 2.4
Name: specpink
Version: 0.1.0
Summary: Spectroscopy reduction pipeline
Author-email: Andreas Bachofner <a12027808@unet.univie.ac.at>
License: MIT
License-File: LICENSE
Requires-Dist: numpy
Requires-Dist: scipy
Requires-Dist: matplotlib
Requires-Dist: astropy
Dynamic: license-file
